dataglasses/__init__.py
dataglasses/core.py
dataglasses/py.typed
dataglasses-0.8.0.dist-info/METADATA
dataglasses-0.8.0.dist-info/WHEEL
dataglasses-0.8.0.dist-info/licenses/LICENSE
dataglasses-0.8.0.dist-info/RECORD
