Metadata-Version: 2.4
Name: dataglasses
Version: 0.8.0
Summary: Simple creation of dataclasses from JSON
Author-email: Uri Granta <uri.granta+python@gmail.com>
License: MIT
License-File: LICENSE
Keywords: dataclasses,json,json schema
Classifier: Development Status :: 4 - Beta
Classifier: Intended Audience :: Developers
Classifier: License :: OSI Approved :: MIT License
Classifier: Operating System :: OS Independent
Classifier: Programming Language :: Python
Classifier: Programming Language :: Python :: 3.10
Classifier: Programming Language :: Python :: 3.11
Classifier: Programming Language :: Python :: 3.12
Classifier: Programming Language :: Python :: 3.13
Classifier: Topic :: File Formats :: JSON
Classifier: Topic :: File Formats :: JSON :: JSON Schema
Requires-Python: >=3.10
